napari_sam/__init__.py
napari_sam/_widget.py
napari_sam/napari.yaml
napari_sam/slicer.py
napari_sam/utils.py
napari_sam-0.4.13.dist-info/LICENSE
napari_sam-0.4.13.dist-info/METADATA
napari_sam-0.4.13.dist-info/WHEEL
napari_sam-0.4.13.dist-info/entry_points.txt
napari_sam-0.4.13.dist-info/top_level.txt
napari_sam-0.4.13.dist-info/RECORD
