Metadata-Version: 2.1
Name: napari-sam
Version: 0.4.13
Summary: Segment anything with Meta AI's new SAM model!
Home-page: https://github.com/MIC-DKFZ/napari-sam
Author: Karol Gotkowski
Author-email: karol.gotkowski@dkfz.de
License: Apache-2.0
Project-URL: Bug Tracker, https://github.com/MIC-DKFZ/napari-sam/issues
Project-URL: Documentation, https://github.com/MIC-DKFZ/napari-sam#README.md
Project-URL: Source Code, https://github.com/MIC-DKFZ/napari-sam
Project-URL: User Support, https://github.com/MIC-DKFZ/napari-sam/issues
Classifier: Development Status :: 2 - Pre-Alpha
Classifier: Framework :: napari
Classifier: Intended Audience :: Developers
Classifier: License :: OSI Approved :: Apache Software License
Classifier: Operating System :: OS Independent
Classifier: Programming Language :: Python
Classifier: Programming Language :: Python :: 3
Classifier: Programming Language :: Python :: 3 :: Only
Classifier: Programming Language :: Python :: 3.8
Classifier: Programming Language :: Python :: 3.9
Classifier: Programming Language :: Python :: 3.10
Classifier: Topic :: Scientific/Engineering :: Image Processing
Requires-Python: >=3.8
License-File: LICENSE
Requires-Dist: numpy
Requires-Dist: magicgui
Requires-Dist: qtpy
Requires-Dist: napari
Requires-Dist: vispy
Requires-Dist: tqdm
Requires-Dist: napari-nifti
Requires-Dist: superqt
Provides-Extra: testing
Requires-Dist: tox ; extra == 'testing'
Requires-Dist: pytest ; extra == 'testing'
Requires-Dist: pytest-cov ; extra == 'testing'
Requires-Dist: pytest-qt ; extra == 'testing'
Requires-Dist: napari ; extra == 'testing'
Requires-Dist: pyqt5 ; extra == 'testing'
